NTBEA-0.0.2.dist-info/DESCRIPTION.rst
NTBEA-0.0.2.dist-info/METADATA
NTBEA-0.0.2.dist-info/RECORD
NTBEA-0.0.2.dist-info/WHEEL
NTBEA-0.0.2.dist-info/metadata.json
NTBEA-0.0.2.dist-info/top_level.txt
ntbea/__init__.py
ntbea/ntbea.py
ntbea/common/__init__.py
ntbea/common/common.py
