Metadata-Version: 2.0
Name: NTBEA
Version: 0.0.2
Summary: N-Tuple Evolutionary Algorithm
Home-page: https://github.com/bam4d/NTBEA
Author: Chris Bamford
Author-email: chrisbam4d@gmail.com
License: UNKNOWN
Platform: UNKNOWN
Classifier: Programming Language :: Python :: 3
Classifier: License :: OSI Approved :: GNU General Public License v3 (GPLv3)
Classifier: Operating System :: OS Independent
